aws_assume_role_otp/__init__.py
aws_assume_role_otp/config.py
aws_assume_role_otp/credentials.py
aws_assume_role_otp/encryption.py
aws_assume_role_otp/main.py
aws_assume_role_otp/sts.py
aws_assume_role_otp-0.3.dist-info/LICENSE
aws_assume_role_otp-0.3.dist-info/METADATA
aws_assume_role_otp-0.3.dist-info/WHEEL
aws_assume_role_otp-0.3.dist-info/entry_points.txt
aws_assume_role_otp-0.3.dist-info/top_level.txt
aws_assume_role_otp-0.3.dist-info/RECORD
